elo_viz/__init__.py
elo_viz/constants.py
elo_viz/elo.py
elo_viz/matches.py
elo_viz/player.py
elo_viz/rating.py
elo_viz-0.0.2.dist-info/LICENSE
elo_viz-0.0.2.dist-info/METADATA
elo_viz-0.0.2.dist-info/WHEEL
elo_viz-0.0.2.dist-info/RECORD
