Metadata-Version: 2.3
Name: elo-viz
Version: 0.0.2
Summary: Elo python package to simulate matches between players, and compare their elo ratings after each match, and visualize it.
License: MIT
Keywords: elo,elo-score,rating,chess,ranking,score
Author: Anurag Shenoy
Author-email: anuragshenoy21@gmail.com
Requires-Python: >=3.13,<4.0
Classifier: Development Status :: 2 - Pre-Alpha
Classifier: Environment :: Console
Classifier: Intended Audience :: Developers
Classifier: Intended Audience :: Education
Classifier: License :: OSI Approved :: MIT License
Classifier: Natural Language :: English
Classifier: Operating System :: OS Independent
Classifier: Programming Language :: Python :: 3
Classifier: Programming Language :: Python :: 3.13
Classifier: Topic :: Education
Classifier: Topic :: Games/Entertainment
Classifier: Topic :: Games/Entertainment :: Board Games
Requires-Dist: ipykernel (>=6.29.5,<7.0.0)
Project-URL: Documentation, https://github.com/shenoy-anurag/elo
Project-URL: Funding, https://buymeacoffee.com/anuragshenoy
Project-URL: Homepage, https://github.com/shenoy-anurag/elo
Project-URL: Issues, https://github.com/shenoy-anurag/elo/issues
Project-URL: Repository, https://github.com/shenoy-anurag/elo
